opencdms_cli/__init__.py
opencdms_cli/cli/__init__.py
opencdms_cli/db/__init__.py
opencdms_cli/db/ports.py
opencdms-0.1.6.dist-info/AUTHORS.md
opencdms-0.1.6.dist-info/LICENSE
opencdms-0.1.6.dist-info/METADATA
opencdms-0.1.6.dist-info/WHEEL
opencdms-0.1.6.dist-info/entry_points.txt
opencdms-0.1.6.dist-info/top_level.txt
opencdms-0.1.6.dist-info/RECORD
