Metadata-Version: 2.1
Name: opencdms
Version: 0.1.6
Summary: OpenCDMS Python package
Home-page: https://www.opencdms.org
Author: OpenCDMS
Author-email: info@opencdms.org
Maintainer: Ian Edwards
Maintainer-email: info@opencdms.org
License: MIT license
Keywords: opencdms
Classifier: Development Status :: 2 - Pre-Alpha
Classifier: Intended Audience :: Developers
Classifier: License :: OSI Approved :: MIT License
Classifier: Natural Language :: English
Classifier: Programming Language :: Python :: 3
Classifier: Programming Language :: Python :: 3.7
Classifier: Programming Language :: Python :: 3.8
Classifier: Programming Language :: Python :: 3.9
Requires-Python: >=3.7
License-File: LICENSE
License-File: AUTHORS.md
Requires-Dist: click
